kitconcept/solr/__init__.py
kitconcept/solr/configure.zcml
kitconcept/solr/dependencies.zcml
kitconcept/solr/interfaces.py
kitconcept/solr/profiles.zcml
kitconcept/solr/reindex_helpers.py
kitconcept/solr/setuphandlers.py
kitconcept/solr/testing.py
kitconcept/solr/behaviors/__init__.py
kitconcept/solr/behaviors/configure.zcml
kitconcept/solr/indexers/configure.zcml
kitconcept/solr/indexers/text.py
kitconcept/solr/locales/__init__.py
kitconcept/solr/locales/__main__.py
kitconcept/solr/locales/kitconcept.solr.pot
kitconcept/solr/locales/de/LC_MESSAGES/kitconcept.solr.mo
kitconcept/solr/locales/de/LC_MESSAGES/kitconcept.solr.po
kitconcept/solr/locales/de/LC_MESSAGES/plone.mo
kitconcept/solr/locales/de/LC_MESSAGES/plone.po
kitconcept/solr/profiles/default/browserlayer.xml
kitconcept/solr/profiles/default/metadata.xml
kitconcept/solr/profiles/default/registry/kitconcept.solr.interfaces.IKitconceptSolrSettings.xml
kitconcept/solr/profiles/testing/metadata.xml
kitconcept/solr/profiles/testing/types.xml
kitconcept/solr/profiles/testing/registry/plone.i18n.interfaces.ILanguageSchema.xml
kitconcept/solr/profiles/testing/types/.gitkeep
kitconcept/solr/profiles/uninstall/browserlayer.xml
kitconcept/solr/services/__init__.py
kitconcept/solr/services/configure.zcml
kitconcept/solr/services/site.py
kitconcept/solr/services/solr.py
kitconcept/solr/services/solr_utils.py
kitconcept/solr/services/suggest.py
kitconcept/solr/upgrades/__init__.py
kitconcept/solr/upgrades/configure.zcml
kitconcept_solr-2.0.0a5.dist-info/METADATA
kitconcept_solr-2.0.0a5.dist-info/WHEEL
kitconcept_solr-2.0.0a5.dist-info/entry_points.txt
kitconcept_solr-2.0.0a5.dist-info/licenses/LICENSE.GPL
kitconcept_solr-2.0.0a5.dist-info/licenses/LICENSE.md
kitconcept_solr-2.0.0a5.dist-info/RECORD
