Metadata-Version: 2.4
Name: kitconcept.solr
Version: 2.0.0a5
Summary: An opinionated Solr integration for Plone.
Project-URL: Homepage, https://github.com/kitconcept/kitconcept-solr
Project-URL: PyPI, https://pypi.org/project/kitconcept.solr
Project-URL: Source, https://github.com/kitconcept/kitconcept-solr
Project-URL: Tracker, https://github.com/kitconcept/kitconcept-solr/issues
Author-email: kitconcept GmbH <info@kitconcept.com>
License-Expression: GPL-2.0-only
License-File: LICENSE.GPL
License-File: LICENSE.md
Keywords: CMS,Plone,Python
Classifier: Development Status :: 3 - Alpha
Classifier: Environment :: Web Environment
Classifier: Framework :: Plone
Classifier: Framework :: Plone :: 6.1
Classifier: Framework :: Plone :: Addon
Classifier: License :: OSI Approved :: GNU General Public License v2 (GPLv2)
Classifier: Operating System :: OS Independent
Classifier: Programming Language :: Python
Classifier: Programming Language :: Python :: 3.12
Classifier: Programming Language :: Python :: 3.13
Requires-Python: >=3.12
Requires-Dist: collective-solr>=9.0.1
Requires-Dist: plone-api
Requires-Dist: plone-app-multilingual
Requires-Dist: plone-restapi
Requires-Dist: plone-volto
Requires-Dist: products-cmfplone
Provides-Extra: test
Requires-Dist: horse-with-no-namespace; extra == 'test'
Requires-Dist: plone-app-testing; extra == 'test'
Requires-Dist: plone-restapi[test]; extra == 'test'
Requires-Dist: pytest; extra == 'test'
Requires-Dist: pytest-cov; extra == 'test'
Requires-Dist: pytest-docker; extra == 'test'
Requires-Dist: pytest-plone; extra == 'test'
